History.rst
LICENSE.txt
MANIFEST.in
README.rst
constraints.txt
requirements.txt
requirements_conda.txt
requirements_read_the_docs.txt
setup.cfg
setup.py
bin/qicolorize
bin/qicolorlut
bin/qipipe
bin/reorder_bolero_mask
qipipe/__init__.py
qipipe.egg-info/PKG-INFO
qipipe.egg-info/SOURCES.txt
qipipe.egg-info/dependency_links.txt
qipipe.egg-info/requires.txt
qipipe.egg-info/top_level.txt
qipipe/conf/__init__.py
qipipe/conf/breast.cfg
qipipe/conf/ctp.cfg
qipipe/conf/default.cfg
qipipe/conf/mask.cfg
qipipe/conf/modeling.cfg
qipipe/conf/qipipeline.cfg
qipipe/conf/registration.cfg
qipipe/conf/roi.cfg
qipipe/conf/sarcoma.cfg
qipipe/conf/staging.cfg
qipipe/helpers/__init__.py
qipipe/helpers/bolus_arrival.py
qipipe/helpers/colors.py
qipipe/helpers/command.py
qipipe/helpers/constants.py
qipipe/helpers/distributable.py
qipipe/helpers/image.py
qipipe/helpers/logging.py
qipipe/helpers/metadata.py
qipipe/helpers/roi.py
qipipe/interfaces/__init__.py
qipipe/interfaces/compress.py
qipipe/interfaces/convert_bolero_mask.py
qipipe/interfaces/copy.py
qipipe/interfaces/dce_to_r1.py
qipipe/interfaces/fastfit.py
qipipe/interfaces/fix_dicom.py
qipipe/interfaces/group_dicom.py
qipipe/interfaces/interface_error.py
qipipe/interfaces/lookup.py
qipipe/interfaces/map_ctp.py
qipipe/interfaces/move.py
qipipe/interfaces/mri_volcluster.py
qipipe/interfaces/preview.py
qipipe/interfaces/reorder_bolero_mask.py
qipipe/interfaces/sticky_identity.py
qipipe/interfaces/touch.py
qipipe/interfaces/uncompress.py
qipipe/interfaces/unpack.py
qipipe/interfaces/update_qiprofile.py
qipipe/interfaces/xnat_copy.py
qipipe/interfaces/xnat_download.py
qipipe/interfaces/xnat_find.py
qipipe/interfaces/xnat_upload.py
qipipe/interfaces/ants/__init__.py
qipipe/interfaces/ants/utils.py
qipipe/pipeline/__init__.py
qipipe/pipeline/mask.py
qipipe/pipeline/modeling.py
qipipe/pipeline/pipeline_error.py
qipipe/pipeline/qipipeline.py
qipipe/pipeline/registration.py
qipipe/pipeline/roi.py
qipipe/pipeline/staging.py
qipipe/pipeline/workflow_base.py
qipipe/qiprofile/__init__.py
qipipe/qiprofile/breast_pathology.py
qipipe/qiprofile/chemotherapy.py
qipipe/qiprofile/clinical.py
