Metadata-Version: 1.1
Name: qipipe
Version: 5.8.1
Summary: Quantitative Imaging Profile pipeline
Home-page: http://qipipe.readthedocs.org/en/latest/
Author: OHSU Knight Cancer Institute
Author-email: loneyf@ohsu.edu
License: MIT
Keywords: Imaging QIN OHSU DCE MR XNAT Nipype
Platform: Any
Classifier: Development Status :: 5 - Production/Stable
Classifier: Topic :: Scientific/Engineering :: Bio-Informatics
Classifier: Environment :: Console
Classifier: Intended Audience :: Science/Research
Classifier: License :: OSI Approved :: MIT License
Classifier: Operating System :: OS Independent
Classifier: Programming Language :: Python
Classifier: Programming Language :: Python :: 2.6
Classifier: Programming Language :: Python :: 2.7
